hulusubs_dl/__init__.py
hulusubs_dl/__main__.py
hulusubs_dl/__version__.py
hulusubs_dl/hulu.py
hulusubs_dl/hulu_api.py
hulusubs_dl/hulu_subs_dl.py
hulusubs_dl/subtitle_processing.py
hulusubs_dl/cust_utils/__init__.py
hulusubs_dl/cust_utils/browser_instance.py
hulusubs_dl/cust_utils/path_util.py
hulusubs_dl/cust_utils/utils.py
hulusubs_dl-2021.1.8.2.dist-info/LICENSE
hulusubs_dl-2021.1.8.2.dist-info/METADATA
hulusubs_dl-2021.1.8.2.dist-info/WHEEL
hulusubs_dl-2021.1.8.2.dist-info/top_level.txt
hulusubs_dl-2021.1.8.2.dist-info/RECORD
