Metadata-Version: 2.1
Name: hulusubs-dl
Version: 2021.1.8.2
Summary: hulusubs_dl is a command line tool to download subtitles from Hulu.
Home-page: https://github.com/Xonshiz/Hulu-Subs-Downloader
Author: Xonshiz
Author-email: xonshiz@gmail.com
License: UNKNOWN
Download-URL: https://github.com/Xonshiz/Hulu-Subs-Downloader/releases/latest
Platform: UNKNOWN
Classifier: Programming Language :: Python :: 3
Classifier: License :: OSI Approved :: MIT License
Classifier: Operating System :: OS Independent
Requires-Python: >=2.6
